Metadata-Version: 2.1
Name: bigraph-builder
Version: 0.0.4
Summary: UNKNOWN
Home-page: https://github.com/vivarium-collective/bigraph-builder
Author: Eran Agmon, Ryan Spangler
Author-email: agmon.eran@gmail.com, ryan.spangler@gmail.com
License: UNKNOWN
Platform: UNKNOWN
Classifier: License :: OSI Approved :: Apache Software License
Classifier: Programming Language :: Python
Classifier: Programming Language :: Python :: 3.9
Classifier: Programming Language :: Python :: 3.10
Classifier: Programming Language :: Python :: 3.11
Requires-Python: >=3.6
License-File: LICENSE
License-File: AUTHORS.md
